<?xml version="1.0" encoding="UTF-8" ?>
<!DOCTYPE mapper PUBLIC "-//mybatis.org//DTD Mapper 3.0//EN"
		    "http://mybatis.org/dtd/mybatis-3-mapper.dtd">
<mapper namespace="com.health.dao.CartDAO" >
	
	<select id="cartQueryById" resultType="CartDTO"
		parameterType="int"> 
	<![CDATA[ 
		SELECT prod_num, product_count FROM cart_table where m_num=#{m_num}
	]]>
	</select>
	<select id="prodQueryByProdNum" resultType="ProductDTO"
		parameterType="int"> 
	<![CDATA[ 
		SELECT * FROM product_table where prod_num=#{prod_num}
	]]>
	</select>
	
	<update id="updateQuan" parameterType="hashMap">
		<![CDATA[ 
		update cart_table set product_count = #{product_count} where prod_num=#{prod_num} and m_num=#{m_num} 
	]]>
	</update>


	<insert id="insertCart" parameterType="hashMap">
		<![CDATA[
			insert into cart_table( m_num, prod_num, product_count )
			values(#{m_num}, #{prod_num}, #{product_count})
		]]>
	</insert>
	
	<delete id="deleteCart" parameterType="hashMap"> 
	<![CDATA[ 
		delete from cart_table where prod_num=#{prod_num} and m_num=#{m_num}
	]]>
	</delete>
	
	<delete id="deleteCartAll" parameterType="String"> 
	<![CDATA[ 
		delete from cart_table WHERE m_num = #{m_num}
	]]>
	</delete>

</mapper>   
